dynaddrmgr/__init__.py
dynaddrmgr/app.py
dynaddrmgr/constants.py
dynaddrmgr/dynhost.py
dynaddrmgr/dynrules.py
dynaddrmgr/dyntmpls.py
dynaddrmgr/foos.py
dynaddrmgr/fwhdlr.py
dynaddrmgr/kinds.py
dynaddrmgr/py.typed
dynaddrmgr/rule.py
dynaddrmgr/singles.py
dynaddrmgr/tmplmgr.py
dynaddrmgr/ufw.py
dynaddrmgr-0.8.2.dist-info/LICENSE
dynaddrmgr-0.8.2.dist-info/METADATA
dynaddrmgr-0.8.2.dist-info/WHEEL
dynaddrmgr-0.8.2.dist-info/entry_points.txt
dynaddrmgr-0.8.2.dist-info/RECORD
