Metadata-Version: 2.3
Name: dynaddrmgr
Version: 0.8.2
Summary: Tools to manage actions based on dynamic host address changes.
License: MIT
Author: Quien Sabe
Author-email: qs5779@mail.com
Requires-Python: >=3.10,<4.0
Classifier: Development Status :: 3 - Alpha
Classifier: Intended Audience :: Developers
Classifier: License :: OSI Approved :: MIT License
Classifier: Operating System :: OS Independent
Classifier: Programming Language :: Python :: 3
Classifier: Programming Language :: Python :: 3.10
Classifier: Programming Language :: Python :: 3.11
Classifier: Programming Language :: Python :: 3.12
Classifier: Programming Language :: Python :: 3.13
Classifier: Programming Language :: Python :: 3 :: Only
Classifier: Topic :: Software Development :: Libraries :: Python Modules
Classifier: Typing :: Typed
Requires-Dist: click (>=8.1.0,<9.0.0)
Requires-Dist: dailylog-lib (>=0.2.2,<0.3.0)
Requires-Dist: dnspython (>=2.4.2,<3.0.0)
Requires-Dist: jinja2 (>=3.1.2,<4.0.0)
Requires-Dist: nslookup (>=1.7.0,<2.0.0)
Requires-Dist: wtforglib (>=1.2.1)
Project-URL: Repository, https://github.com/wtfo-guru/dynaddrmgr
